README.md
portube.py
setup.py
portube.egg-info/PKG-INFO
portube.egg-info/SOURCES.txt
portube.egg-info/dependency_links.txt
portube.egg-info/entry_points.txt
portube.egg-info/top_level.txt