Metadata-Version: 1.1
Name: portube
Version: 0.0.1
Summary: Software-implemented port forwarding, transparent proxy, which can bypass firewalls in specific cases where the host restricts the inbound rules but does not restrict the outbound rules
Home-page: https://github.com/loser007/Portube
Author: dbsven
Author-email: 501287441@qq.com
License: BSD License
Keywords: portmap tunnel tube protube
Platform: all
Classifier: Development Status :: 4 - Beta
Classifier: Intended Audience :: Developers
Classifier: Topic :: Software Development :: Libraries :: Python Modules
Classifier: License :: OSI Approved :: Apache Software License
Classifier: Programming Language :: Python
Classifier: Programming Language :: Python :: 2
Classifier: Programming Language :: Python :: 2.7
Classifier: Programming Language :: Python :: 3
Classifier: Programming Language :: Python :: 3.4
Classifier: Programming Language :: Python :: 3.5
Classifier: Programming Language :: Python :: 3.6
Classifier: Programming Language :: Python :: 3.7
Classifier: Operating System :: OS Independent
Classifier: Operating System :: POSIX
Classifier: Operating System :: MacOS
Classifier: Operating System :: Unix
